_godopy.cpython-38-darwin.so
godot_tools/__init__.py
godot_tools/cli.py
godot_tools/utils.py
godot_tools/version.py
godot_tools/binding_generator/__init__.py
godot_tools/binding_generator/pxd_writer.py
godot_tools/binding_generator/templates/__cython_icalls.hpp.mako
godot_tools/binding_generator/templates/__cython_icalls.pxd.mako
godot_tools/binding_generator/templates/__python_icalls.hpp.mako
godot_tools/binding_generator/templates/__python_icalls.pxd.mako
godot_tools/binding_generator/templates/_cpp_bindings.pxd.mako
godot_tools/binding_generator/templates/_cython_bindings.pxd.mako
godot_tools/binding_generator/templates/_cython_bindings.pyx.mako
godot_tools/binding_generator/templates/_python_bindings.pxd.mako
godot_tools/binding_generator/templates/_python_bindings.pyx.mako
godot_tools/binding_generator/templates/cpp_module.pxd.mako
godot_tools/binding_generator/templates/cython_module.pxd.mako
godot_tools/binding_generator/templates/python_module.py.mako
godot_tools/script_runner/__init__.py
godot_tools/script_runner/project.py
godot_tools/setup/__init__.py
godot_tools/setup/enums.py
godot_tools/setup/extensions.py
godot_tools/setup/libraries.py
godot_tools/setup/templates/SConstruct.mako
godot_tools/setup/templates/gdlibrary.cpp.mako
godot_tools/setup/templates/gdnlib.mako
godot_tools/setup/templates/gdns.mako
godot_tools/setup/templates/library_setup.gd.mako
godot_tools/setup/templates/plugin.cfg.mako
godot_tools/tests/__init__.py
godot_tools/tests/runtests.py
GodoPy-0.0.3.dist-info/LICENSE.md
GodoPy-0.0.3.dist-info/METADATA
GodoPy-0.0.3.dist-info/WHEEL
GodoPy-0.0.3.dist-info/entry_points.txt
GodoPy-0.0.3.dist-info/top_level.txt
GodoPy-0.0.3.dist-info/RECORD
